odoo/addons/survey_link_base/README.rst
odoo/addons/survey_link_base/__init__.py
odoo/addons/survey_link_base/__manifest__.py
odoo/addons/survey_link_base/i18n/es.po
odoo/addons/survey_link_base/i18n/it.po
odoo/addons/survey_link_base/i18n/survey_link_base.pot
odoo/addons/survey_link_base/models/__init__.py
odoo/addons/survey_link_base/models/survey_link_mixin.py
odoo/addons/survey_link_base/models/survey_survey.py
odoo/addons/survey_link_base/models/survey_user_input.py
odoo/addons/survey_link_base/readme/CONTRIBUTORS.rst
odoo/addons/survey_link_base/readme/DESCRIPTION.rst
odoo/addons/survey_link_base/readme/USAGE.rst
odoo/addons/survey_link_base/security/ir.model.access.csv
odoo/addons/survey_link_base/static/description/icon.png
odoo/addons/survey_link_base/static/description/index.html
odoo/addons/survey_link_base/tests/__init__.py
odoo/addons/survey_link_base/tests/models.py
odoo/addons/survey_link_base/tests/test_survey_link_base.py
odoo/addons/survey_link_base/tests/test_survey_link_mixin.py
odoo/addons/survey_link_base/wizard/__init__.py
odoo/addons/survey_link_base/wizard/survey_link_wizard.py
odoo/addons/survey_link_base/wizard/survey_link_wizard_views.xml
odoo_addon_survey_link_base-16.0.1.0.0.3.dist-info/METADATA
odoo_addon_survey_link_base-16.0.1.0.0.3.dist-info/WHEEL
odoo_addon_survey_link_base-16.0.1.0.0.3.dist-info/top_level.txt
odoo_addon_survey_link_base-16.0.1.0.0.3.dist-info/RECORD
